./.env.example
./.gitignore
./.python-version
./.rules
./CHANGELOG.md
./CONTRIBUTING.md
./LICENSE
./LOGGING.md
./MANIFEST.in
./PKG-INFO
./README.md
./__init__.py
./main.py
./main_sse.py
./pyproject.toml
./pytest.ini
./server.py
./uv.lock
./.github/instructions/dev_workflow.instructions.md
./.github/instructions/self_improve.instructions.md
./.github/instructions/taskmaster.instructions.md
./.github/instructions/vscode_rules.instructions.md
./.github/workflows/publish.yml
./.github/workflows/test.yml
./config/token.json.example
./docs/README.md
./docs/api-reference.md
./docs/configuration.md
./docs/examples.md
./docs/getting-started.md
./docs/installation-guide.md
./docs/installation.md
./docs/troubleshooting.md
./tests/__init__.py
./tests/test_basic.py
./tests/test_command_tools.py
./tests/test_events_tools.py
./tests/test_http_client.py
./tests/test_iam_tools.py
./tests/test_metrics_tools.py
./tests/test_server_tools.py
./tests/test_simple_integration.py
./tests/test_system_info_tools.py
./tests/test_system_tools.py
./tests/test_webftp_tools.py
./tests/test_websh_tools.py
./tests/test_workspace_tools.py
./tools/command_tools.py
./tools/events_tools.py
./tools/iam_tools.py
./tools/metrics_tools.py
./tools/server_tools.py
./tools/system_info_tools.py
./tools/webftp_tools.py
./tools/websh_tools.py
./tools/workspace_tools.py
./utils/common.py
./utils/decorators.py
./utils/error_handler.py
./utils/http_client.py
./utils/logger.py
./utils/setup_wizard.py
./utils/token_manager.py
alpacon_mcp-0.4.3.dist-info/METADATA
alpacon_mcp-0.4.3.dist-info/WHEEL
alpacon_mcp-0.4.3.dist-info/entry_points.txt
alpacon_mcp-0.4.3.dist-info/licenses/LICENSE
alpacon_mcp-0.4.3.dist-info/RECORD
