Metadata-Version: 2.4
Name: alpacon-mcp
Version: 0.4.3
Summary: AI-Powered Server Management - Connect Claude, Cursor, and other AI tools directly to your Alpacon infrastructure
Project-URL: Homepage, https://github.com/alpacax/alpacon-mcp
Project-URL: Documentation, https://github.com/alpacax/alpacon-mcp/blob/main/docs/README.md
Project-URL: Repository, https://github.com/alpacax/alpacon-mcp.git
Project-URL: Issues, https://github.com/alpacax/alpacon-mcp/issues
Project-URL: Changelog, https://github.com/alpacax/alpacon-mcp/blob/main/CHANGELOG.md
Author-email: Alpacon Team <support@alpacon.io>
Maintainer-email: Alpacon Team <support@alpacon.io>
License: MIT
License-File: LICENSE
Keywords: ai,alpacon,claude,cursor,infrastructure,mcp,model-context-protocol,monitoring,server-management
Classifier: Development Status :: 4 - Beta
Classifier: Environment :: Console
Classifier: Intended Audience :: Developers
Classifier: Intended Audience :: System Administrators
Classifier: License :: OSI Approved :: MIT License
Classifier: Operating System :: OS Independent
Classifier: Programming Language :: Python :: 3
Classifier: Programming Language :: Python :: 3.12
Classifier: Topic :: Software Development :: Libraries :: Python Modules
Classifier: Topic :: System :: Monitoring
Classifier: Topic :: System :: Systems Administration
Requires-Python: >=3.12
Requires-Dist: httpx>=0.25.0
Requires-Dist: mcp[cli]>=1.9.4
Requires-Dist: websockets>=15.0.1
Provides-Extra: dev
Requires-Dist: black>=23.0.0; extra == 'dev'
Requires-Dist: flake8>=6.0.0; extra == 'dev'
Requires-Dist: isort>=5.12.0; extra == 'dev'
Requires-Dist: mypy>=1.0.0; extra == 'dev'
Requires-Dist: pytest-asyncio>=0.21.0; extra == 'dev'
Requires-Dist: pytest>=7.0.0; extra == 'dev'
